odoo10_addon_sale_product_multi_add-10.0.1.0.1-py3.8-nspkg.pth
odoo/addons/sale_product_multi_add/README.rst
odoo/addons/sale_product_multi_add/__init__.py
odoo/addons/sale_product_multi_add/__manifest__.py
odoo/addons/sale_product_multi_add/i18n/ca.po
odoo/addons/sale_product_multi_add/i18n/es.po
odoo/addons/sale_product_multi_add/i18n/sale_product_multi_add.pot
odoo/addons/sale_product_multi_add/static/description/icon.png
odoo/addons/sale_product_multi_add/tests/__init__.py
odoo/addons/sale_product_multi_add/tests/test_sale.py
odoo/addons/sale_product_multi_add/views/sale_view.xml
odoo/addons/sale_product_multi_add/wizards/__init__.py
odoo/addons/sale_product_multi_add/wizards/sale_import_products.py
odoo/addons/sale_product_multi_add/wizards/sale_import_products_view.xml
odoo10_addon_sale_product_multi_add-10.0.1.0.1.dist-info/METADATA
odoo10_addon_sale_product_multi_add-10.0.1.0.1.dist-info/WHEEL
odoo10_addon_sale_product_multi_add-10.0.1.0.1.dist-info/namespace_packages.txt
odoo10_addon_sale_product_multi_add-10.0.1.0.1.dist-info/top_level.txt
odoo10_addon_sale_product_multi_add-10.0.1.0.1.dist-info/RECORD
